adagradw/__init__.py
adagradw/adagradw.py
adagradw-0.0.4.dist-info/METADATA
adagradw-0.0.4.dist-info/WHEEL
adagradw-0.0.4.dist-info/top_level.txt
adagradw-0.0.4.dist-info/RECORD
