Metadata-Version: 2.1
Name: adagradw
Version: 0.0.4
Summary: AdagradW - Decoupled Weight Decay in Adagrad
Author-email: "Richard D. Paul" <richard@los-paul.eu>
Classifier: Programming Language :: Python :: 3
Classifier: Operating System :: OS Independent
Requires-Python: >=3.10
Requires-Dist: torch<=2.1
